[{"possibly_sensitive":false,"author_id":"343663197","id":"406053028739833856","lang":"no","edit_history_tweet_ids":["406053028739833856"],"entities":{"urls":[{"start":39,"end":61,"url":"http://t.co/xaTVhKFf3y","expanded_url":"http://avpixlat.info/2013/11/28/debatt-jan-guillou-och-pia-kjaersgaard/..#svpol","display_url":"avpixlat.info/2013/11/28/deb…"}],"mentions":{},"hashtags":{}},"public_metrics":{"retweet_count":0,"reply_count":2,"like_count":0,"quote_count":0,"bookmark_count":0,"impression_count":0},"created_at":"2013-11-28T13:32:40.000Z","conversation_id":"406053028739833856","text":"Debatt: Jan Guillou och Pia Kjærsgaard http://t.co/xaTVhKFf3y","referenced_tweets":{},"attachments":{"media_keys":{}},"geo":{"coordinates":{"coordinates":{}}}},{"possibly_sensitive":false,"author_id":"25984830","id":"743492915058589696","lang":"da","edit_history_tweet_ids":["743492915058589696"],"entities":{"urls":{},"mentions":[{"start":0,"end":8,"username":"yo_ELOQ","id":"18337005"},{"start":9,"end":25,"username":"blackmadonnachi","id":"1279481500619223040"}],"hashtags":{}},"public_metrics":{"retweet_count":0,"reply_count":1,"like_count":0,"quote_count":0,"bookmark_count":0,"impression_count":0},"created_at":"2016-06-16T17:18:19.000Z","conversation_id":"743483676613304321","text":"@yo_ELOQ @blackmadonnachi Damn, det gad jeg godt! Enjoy!","referenced_tweets":[{"type":"replied_to","id":"743483676613304321"}],"in_reply_to_user_id":"18337005","attachments":{"media_keys":{}},"geo":{"coordinates":{"coordinates":{}}}},{"possibly_sensitive":false,"author_id":"606561223","id":"1439185923300810758","lang":"da","edit_history_tweet_ids":["1439185923300810758"],"entities":{"urls":[{"start":233,"end":256,"url":"https://t.co/Vst95tlHxe","expanded_url":"https://politiken.dk/indland/art8384100/Hun-er-færdig-med-corona-og-vil-spille-meget-større-klimarolle","display_url":"politiken.dk/indland/art838…","status":200,"unwound_url":"https://politiken.dk/danmark/art8384100/Statsministeren-er-f%C3%A6rdig-med-corona-og-vil-spille-meget-st%C3%B8rre-klimarolle"}],"mentions":{},"hashtags":[{"start":226,"end":232,"tag":"dkpol"}]},"public_metrics":{"retweet_count":7,"reply_count":14,"like_count":67,"quote_count":1,"bookmark_count":0,"impression_count":0},"created_at":"2021-09-18T11:13:57.000Z","conversation_id":"1439185923300810758","text":"Stærk grøn start på S-kongres af statsministeren🌹💚\n“Klimaforandringerne vil ske hurtigere, end vi troede. Lad mig i dag gøre det helt klart. Landbruget skal selvfølgelig have et bindende klimamål.” Det er nu, der skal handles #dkpol https://t.co/Vst95tlHxe","referenced_tweets":{},"attachments":{"media_keys":{}},"geo":{"coordinates":{"coordinates":{}}}},{"possibly_sensitive":false,"author_id":"253632840","id":"574643210171121664","lang":"da","edit_history_tweet_ids":["574643210171121664"],"entities":{"urls":{},"mentions":[{"start":0,"end":8,"username":"PruPruh","id":"155354125"}],"hashtags":{}},"public_metrics":{"retweet_count":0,"reply_count":1,"like_count":0,"quote_count":0,"bookmark_count":0,"impression_count":0},"created_at":"2015-03-08T18:49:52.000Z","conversation_id":"574634217260326912","text":"@PruPruh Tak :) Fandt du et link? @MThaastrup","referenced_tweets":[{"type":"replied_to","id":"574634217260326912"}],"in_reply_to_user_id":"155354125","attachments":{"media_keys":{}},"geo":{"coordinates":{"coordinates":{}}}},{"possibly_sensitive":false,"author_id":"1273274477846179847","id":"1322249822892625921","lang":"da","edit_history_tweet_ids":["1322249822892625921"],"entities":{"urls":{},"mentions":[{"start":0,"end":12,"username":"MThoregaard","id":"1172175937"},{"start":13,"end":25,"username":"jespertagen","id":"1663355071"},{"start":26,"end":42,"username":"NicklasSNielse2","id":"4236991977"}],"hashtags":{}},"public_metrics":{"retweet_count":0,"reply_count":1,"like_count":0,"quote_count":0,"bookmark_count":0,"impression_count":0},"created_at":"2020-10-30T18:51:38.000Z","conversation_id":"1322175358330949636","text":"@MThoregaard @jespertagen @NicklasSNielse2 Hvad er blas?","referenced_tweets":[{"type":"replied_to","id":"1322246380996513794"}],"in_reply_to_user_id":"1172175937","attachments":{"media_keys":{}},"geo":{"coordinates":{"coordinates":{}}}},{"possibly_sensitive":false,"author_id":"831530341","id":"1138884605317124103","lang":"da","edit_history_tweet_ids":["1138884605317124103"],"entities":{"urls":{},"mentions":[{"start":0,"end":16,"username":"MortenBHojgaard","id":"1362192048"}],"hashtags":{}},"public_metrics":{"retweet_count":0,"reply_count":1,"like_count":3,"quote_count":0,"bookmark_count":0,"impression_count":0},"created_at":"2019-06-12T19:03:44.000Z","conversation_id":"1138778537601773570","text":"@MortenBHojgaard Det bliver offentliggjort op til eller i weekenden","referenced_tweets":[{"type":"replied_to","id":"1138884452799721472"}],"in_reply_to_user_id":"1362192048","attachments":{"media_keys":{}},"geo":{"coordinates":{"coordinates":{}}}},{"possibly_sensitive":false,"author_id":"4737240105","id":"1277701116516597766","lang":"da","edit_history_tweet_ids":["1277701116516597766"],"entities":{"urls":{},"mentions":[{"start":0,"end":16,"username":"stinuslindgreen","id":"87923613"},{"start":17,"end":26,"username":"Heunicke","id":"22695562"}],"hashtags":{}},"public_metrics":{"retweet_count":0,"reply_count":1,"like_count":4,"quote_count":0,"bookmark_count":0,"impression_count":0},"created_at":"2020-06-29T20:30:59.000Z","conversation_id":"1277217632501010442","text":"@stinuslindgreen @Heunicke Særligt RIGTIG meget indenfor vægttabsområdet! Glem ikke at invitér os diætister med til et møde.🙏vi bruger snart halvdelen af vores konsultationstid på at afdække myter og fub inden vi kan komme igang med vores videnskabelige og pædagogiske vejledning😉","referenced_tweets":[{"type":"replied_to","id":"1277217632501010442"}],"in_reply_to_user_id":"87923613","attachments":{"media_keys":{}},"geo":{"coordinates":{"coordinates":{}}}},{"possibly_sensitive":false,"author_id":"29420980","id":"1322571411471433728","lang":"da","edit_history_tweet_ids":["1322571411471433728"],"entities":{"urls":{},"mentions":{},"hashtags":[{"start":26,"end":31,"tag":"sldk"}]},"public_metrics":{"retweet_count":0,"reply_count":6,"like_count":11,"quote_count":0,"bookmark_count":0,"impression_count":0},"created_at":"2020-10-31T16:09:31.000Z","conversation_id":"1322571411471433728","text":"Spiller FCM uden målmand? #sldk","referenced_tweets":{},"attachments":{"media_keys":{}},"geo":{"coordinates":{"coordinates":{}}}},{"possibly_sensitive":false,"author_id":"847897136","id":"590167189090656257","lang":"da","edit_history_tweet_ids":["590167189090656257"],"entities":{"urls":{},"mentions":[{"start":0,"end":15,"username":"QvortrupHenrik","id":"28340432"}],"hashtags":{}},"public_metrics":{"retweet_count":0,"reply_count":2,"like_count":3,"quote_count":0,"bookmark_count":0,"impression_count":0},"created_at":"2015-04-20T14:56:37.000Z","conversation_id":"590095176594513920","text":"@QvortrupHenrik Fremragende programmer, du laver, Henrik!","referenced_tweets":[{"type":"replied_to","id":"590095176594513920"}],"in_reply_to_user_id":"28340432","attachments":{"media_keys":{}},"geo":{"coordinates":{"coordinates":{}}}},{"possibly_sensitive":false,"author_id":"2191758915","id":"601287915923218432","lang":"da","edit_history_tweet_ids":["601287915923218432"],"entities":{"urls":{},"mentions":[{"start":0,"end":6,"username":"jaaen","id":"17038747"},{"start":43,"end":49,"username":"jaaen","id":"17038747"}],"hashtags":{}},"public_metrics":{"retweet_count":0,"reply_count":1,"like_count":1,"quote_count":0,"bookmark_count":0,"impression_count":0},"created_at":"2015-05-21T07:26:25.000Z","conversation_id":"601153477444771840","text":"@jaaen @oveucsj og dét er dit handlingsrum @jaaen (og alle andre, der underviser) - dér hvor du kan gøre en væsentlig forskel","referenced_tweets":[{"type":"replied_to","id":"601287726609104897"}],"in_reply_to_user_id":"2191758915","attachments":{"media_keys":{}},"geo":{"coordinates":{"coordinates":{}}}},{"possibly_sensitive":false,"author_id":"3118236147","id":"1055038926883307521","lang":"da","edit_history_tweet_ids":["1055038926883307521"],"entities":{"urls":[{"start":28,"end":51,"url":"https://t.co/INhFkcvzeI","expanded_url":"http://bit.ly/gaa-til-leovegas","display_url":"bit.ly/gaa-til-leoveg…"}],"mentions":{},"hashtags":{}},"public_metrics":{"retweet_count":0,"reply_count":1,"like_count":7,"quote_count":0,"bookmark_count":0,"impression_count":0},"created_at":"2018-10-24T10:10:56.000Z","conversation_id":"1055038925604040705","text":"Alle odds er fra Leo Vegas (https://t.co/INhFkcvzeI), og vi sigter typisk efter i omegnen af odds 1,10 pr. spil, hvilket vil give en mission på at ramme ca. 40 spil i træk i jagten på 5.000 kroner (og 97 spil i jagten på millionen, hvis man er til den slags høje spil 🙂)","referenced_tweets":[{"type":"replied_to","id":"1055038925604040705"}],"in_reply_to_user_id":"3118236147","attachments":{"media_keys":{}},"geo":{"coordinates":{"coordinates":{}}}},{"possibly_sensitive":false,"author_id":"874166718","id":"1498612642503708674","lang":"da","edit_history_tweet_ids":["1498612642503708674"],"entities":{"urls":[{"start":210,"end":233,"url":"https://t.co/r7WgH69RGe","expanded_url":"https://politiken.dk/indland/art8644680/%C2%BBDet-her-lugter-simpelthen-s%C3%A5-langt-v%C3%A6k%C2%AB-St%C3%B8ttepartier-er-i-haserne-p%C3%A5-H%C3%A6kkerup-efter-nyt-folketingssvar","display_url":"politiken.dk/indland/art864…","status":200,"unwound_url":"https://politiken.dk/danmark/art8644680/%C2%BBDet-her-lugter-simpelthen-s%C3%A5-langt-v%C3%A6k%C2%AB-St%C3%B8ttepartier-er-i-haserne-p%C3%A5-H%C3%A6kkerup-efter-nyt-folketingssvar"}],"mentions":[{"start":197,"end":208,"username":"SamiraNawa","id":"92107029"}],"hashtags":[{"start":173,"end":179,"tag":"dkpol"},{"start":180,"end":196,"tag":"EngangVarJegFri"}]},"public_metrics":{"retweet_count":21,"reply_count":2,"like_count":62,"quote_count":3,"bookmark_count":1,"impression_count":0},"created_at":"2022-03-01T10:54:31.000Z","conversation_id":"1498612642503708674","text":"Sagen om ulovlig logning bliver mere og mere absurd. Som anklaget ved Højesteret sørger regeringen for at ændre loven og stoppe sagen, to uger før den skulle for domstolen! #dkpol #EngangVarJegFri @SamiraNawa \nhttps://t.co/r7WgH69RGe","referenced_tweets":{},"attachments":{"media_keys":{}},"geo":{"coordinates":{"coordinates":{}}}},{"possibly_sensitive":false,"author_id":"2644990744","id":"1235287221663563777","lang":"da","edit_history_tweet_ids":["1235287221663563777"],"entities":{"urls":{},"mentions":[{"start":0,"end":10,"username":"baretraet","id":"805874425988087811"}],"hashtags":{}},"public_metrics":{"retweet_count":0,"reply_count":1,"like_count":0,"quote_count":0,"bookmark_count":0,"impression_count":0},"created_at":"2020-03-04T19:33:18.000Z","conversation_id":"1235280513415483393","text":"@baretraet @_OfficialMikael Hov hov ingen grund til at blive grov 😘","referenced_tweets":[{"type":"replied_to","id":"1235286636025479169"}],"in_reply_to_user_id":"805874425988087811","attachments":{"media_keys":{}},"geo":{"coordinates":{"coordinates":{}}}},{"possibly_sensitive":false,"author_id":"251555678","id":"1120386428972802050","lang":"da","edit_history_tweet_ids":["1120386428972802050"],"entities":{"urls":[{"start":16,"end":39,"url":"https://t.co/o6qCvodeaL","expanded_url":"https://twitter.com/_aysaysbaby_/status/1120297270644289536","display_url":"x.com/_aysaysbaby_/s…"}],"mentions":{},"hashtags":{}},"public_metrics":{"retweet_count":0,"reply_count":0,"like_count":0,"quote_count":0,"bookmark_count":0,"impression_count":0},"created_at":"2019-04-22T17:58:35.000Z","conversation_id":"1120386428972802050","text":"Kæft en hat! 😂😂 https://t.co/o6qCvodeaL","referenced_tweets":[{"type":"quoted","id":"1120297270644289536"}],"attachments":{"media_keys":{}},"geo":{"coordinates":{"coordinates":{}}}},{"possibly_sensitive":false,"author_id":"14377345","id":"1238757530484060160","lang":"da","edit_history_tweet_ids":["1238757530484060160"],"entities":{"urls":{},"mentions":[{"start":0,"end":8,"username":"TarpCPH","id":"49061760"},{"start":9,"end":24,"username":"QvortrupHenrik","id":"28340432"},{"start":25,"end":32,"username":"pomaEB","id":"37673304"}],"hashtags":{}},"public_metrics":{"retweet_count":0,"reply_count":4,"like_count":6,"quote_count":0,"bookmark_count":0,"impression_count":0},"created_at":"2020-03-14T09:23:04.000Z","conversation_id":"1238756015660838912","text":"@TarpCPH @QvortrupHenrik @pomaEB Skal vi ikke også være enige om at anbefalingerne potentielt kan være uhensigtsmæssige? Hvordan vil du fx. forholde dig til at Sverige fx. kommer ud på den anden side uden samme gigantiske omk. for alle dem der blev fyret i DK?","referenced_tweets":[{"type":"replied_to","id":"1238756716801556480"}],"in_reply_to_user_id":"49061760","attachments":{"media_keys":{}},"geo":{"coordinates":{"coordinates":{}}}},{"possibly_sensitive":false,"author_id":"188437755","id":"920600918093172736","lang":"da","edit_history_tweet_ids":["920600918093172736"],"entities":{"urls":{},"mentions":[{"start":0,"end":9,"username":"lahoyrup","id":"1628608723"},{"start":10,"end":24,"username":"MortenGlinvad","id":"1619967589"}],"hashtags":{}},"public_metrics":{"retweet_count":0,"reply_count":1,"like_count":0,"quote_count":0,"bookmark_count":0,"impression_count":0},"created_at":"2017-10-18T10:42:17.000Z","conversation_id":"920594504771670016","text":"@lahoyrup @MortenGlinvad Ritzau har faktisk kun overgivet sig halvt. Sproget og tillægsordet kalder vi catalansk. En person fra Catalonien = catalonier.","referenced_tweets":[{"type":"replied_to","id":"920598792730300416"}],"in_reply_to_user_id":"1628608723","attachments":{"media_keys":{}},"geo":{"coordinates":{"coordinates":{}}}},{"possibly_sensitive":false,"author_id":"131443197","id":"1453590880988942338","lang":"da","edit_history_tweet_ids":["1453590880988942338"],"entities":{"urls":{},"mentions":[{"start":0,"end":11,"username":"Stamjaklen","id":"172681835"}],"hashtags":{}},"public_metrics":{"retweet_count":0,"reply_count":1,"like_count":0,"quote_count":0,"bookmark_count":0,"impression_count":0},"created_at":"2021-10-28T05:14:07.000Z","conversation_id":"1453412333540323333","text":"@Stamjaklen Hvis ikke beskederne indeholder persondata, så er GDPR fuldstændig irrelevant.","referenced_tweets":[{"type":"replied_to","id":"1453412333540323333"}],"in_reply_to_user_id":"172681835","attachments":{"media_keys":{}},"geo":{"coordinates":{"coordinates":{}}}},{"possibly_sensitive":false,"author_id":"373959985","id":"1474047112883154950","lang":"da","edit_history_tweet_ids":["1474047112883154950"],"entities":{"urls":{},"mentions":[{"start":0,"end":11,"username":"JonasRimer","id":"49622189"},{"start":12,"end":28,"username":"ammitzbollbille","id":"26210681"},{"start":29,"end":37,"username":"Elbjorn","id":"32342915"},{"start":38,"end":54,"username":"rasmus_bendtsen","id":"569200801"},{"start":55,"end":69,"username":"VibekeBorberg","id":"26222057"},{"start":70,"end":81,"username":"berlingske","id":"15022190"},{"start":82,"end":91,"username":"borsendk","id":"23756846"},{"start":92,"end":106,"username":"Pressenaevnet","id":"743791334008446976"}],"hashtags":{}},"public_metrics":{"retweet_count":0,"reply_count":1,"like_count":1,"quote_count":0,"bookmark_count":0,"impression_count":0},"created_at":"2021-12-23T15:59:52.000Z","conversation_id":"1473584920538894340","text":"@JonasRimer @ammitzbollbille @Elbjorn @rasmus_bendtsen @VibekeBorberg @berlingske @borsendk @Pressenaevnet Sådan er det både at være journalist og advokat. Man går fra sag til sag og man har også en ekspertise med sig. Advokater har en beskyttet profession med skarpe habilitetsregler. Så heldige er vi ikke som journalister. “Interessant” er i bedste fald intrigant IMHO","referenced_tweets":[{"type":"replied_to","id":"1474045875701833730"}],"in_reply_to_user_id":"49622189","attachments":{"media_keys":{}},"geo":{"coordinates":{"coordinates":{}}}},{"possibly_sensitive":false,"author_id":"2262462442","id":"1344639581279428614","lang":"da","edit_history_tweet_ids":["1344639581279428614"],"entities":{"urls":[{"start":106,"end":129,"url":"https://t.co/euQuYZwik6","expanded_url":"https://twitter.com/allankraak/status/1344639581279428614/photo/1","display_url":"pic.twitter.com/euQuYZwik6","media_key":"16_1344639573993918464"}],"mentions":{},"hashtags":{}},"public_metrics":{"retweet_count":0,"reply_count":1,"like_count":6,"quote_count":0,"bookmark_count":0,"impression_count":0},"created_at":"2020-12-31T13:40:33.000Z","conversation_id":"1344639581279428614","text":"Godt Nytår til jer alle, pas på jer selv og hinanden og lad os håbe 2021 bliver betydelig bedre end 2020. https://t.co/euQuYZwik6","referenced_tweets":{},"attachments":{"media_keys":["16_1344639573993918464"]},"geo":{"coordinates":{"coordinates":{}}}},{"possibly_sensitive":false,"author_id":"386775622","id":"937057612243271682","lang":"da","edit_history_tweet_ids":["937057612243271682"],"entities":{"urls":[{"start":253,"end":276,"url":"https://t.co/G4ApuXgYNw","expanded_url":"https://www.dr.dk/nyheder/indland/mine-boern-har-ikke-faaet-julegave-i-flere-aar","display_url":"dr.dk/nyheder/indlan…"}],"mentions":{},"hashtags":[{"start":245,"end":251,"tag":"dkpol"}]},"public_metrics":{"retweet_count":0,"reply_count":1,"like_count":3,"quote_count":0,"bookmark_count":0,"impression_count":0},"created_at":"2017-12-02T20:35:19.000Z","conversation_id":"937057612243271682","text":"Endnu en \"stakkels\" fattig Carina \n\n\"Arbejdsløs\" i 10 år og søgt julehjælp i 20 år\n\n - men har  alligevel råd til at datter har DK dyreste hobby:  Hesteridning!  \n\nDet skal mine skattekroner fanme ikke gå til. \nSæt kontanthjælp ned efter et år. #dkpol\n https://t.co/G4ApuXgYNw","referenced_tweets":{},"attachments":{"media_keys":{}},"geo":{"coordinates":{"coordinates":{}}}},{"possibly_sensitive":false,"author_id":"156239854","id":"1171754456632954885","lang":"da","edit_history_tweet_ids":["1171754456632954885"],"entities":{"urls":[{"start":125,"end":148,"url":"https://t.co/gm8sYNQzBc","expanded_url":"https://www.theatlantic.com/science/archive/2018/02/i-spent-two-years-trying-to-fix-the-gender-imbalance-in-my-stories/552404/","display_url":"theatlantic.com/science/archiv…"}],"mentions":[{"start":0,"end":13,"username":"sidsel_vinge","id":"849905598942633984"}],"hashtags":{}},"public_metrics":{"retweet_count":0,"reply_count":1,"like_count":0,"quote_count":0,"bookmark_count":0,"impression_count":0},"created_at":"2019-09-11T11:56:47.000Z","conversation_id":"1171671714440404992","text":"@sidsel_vinge Nu er jeg ikke journalist, men der er nogle gode argumenter for den process din DR journalistven havde gang i: https://t.co/gm8sYNQzBc - videnskabsformidling er en vigtig del af forskeres arbejde, og hvis der er en bias mod kvinder, er det fint han forsøger gøre noget ved det imo","referenced_tweets":[{"type":"replied_to","id":"1171671725114834944"}],"in_reply_to_user_id":"849905598942633984","attachments":{"media_keys":{}},"geo":{"coordinates":{"coordinates":{}}}},{"possibly_sensitive":false,"author_id":"428093953","id":"576099666577788928","lang":"no","edit_history_tweet_ids":["576099666577788928"],"entities":{"urls":{},"mentions":{},"hashtags":{}},"public_metrics":{"retweet_count":2,"reply_count":11,"like_count":3,"quote_count":0,"bookmark_count":0,"impression_count":0},"created_at":"2015-03-12T19:17:18.000Z","conversation_id":"576099666577788928","text":"På en skala fra 0 til vodka, hvordan har din dag så været?","referenced_tweets":{},"attachments":{"media_keys":{}},"geo":{"coordinates":{"coordinates":{}}}},{"possibly_sensitive":false,"author_id":"1944096307","id":"1383698245910634496","lang":"da","edit_history_tweet_ids":["1383698245910634496"],"entities":{"urls":{},"mentions":[{"start":7,"end":21,"username":"pelledragsted","id":"119879630"},{"start":37,"end":51,"username":"JonasBengtson","id":"51857317"},{"start":68,"end":82,"username":"BjarkeCharlie","id":"1808447293810769920"}],"hashtags":{}},"public_metrics":{"retweet_count":0,"reply_count":1,"like_count":5,"quote_count":0,"bookmark_count":0,"impression_count":0},"created_at":"2021-04-18T08:25:44.000Z","conversation_id":"1383372261839626251","text":"@NVMHP @pelledragsted @FabulesFilajs @JonasBengtson @saraproblemsir @BjarkeCharlie Hun kan ikke danne en S-regering, hvis ikke Ø peger på hende.","referenced_tweets":[{"type":"replied_to","id":"1383697584435253251"}],"in_reply_to_user_id":"3707697327","attachments":{"media_keys":{}},"geo":{"coordinates":{"coordinates":{}}}},{"possibly_sensitive":false,"author_id":"2314618961","id":"515132123297378304","lang":"da","edit_history_tweet_ids":["515132123297378304"],"entities":{"urls":[{"start":106,"end":128,"url":"http://t.co/OIpb4jZIPP","expanded_url":"http://www.e-pages.dk/lederne/94/","display_url":"e-pages.dk/lederne/94/"}],"mentions":[{"start":89,"end":104,"username":"BusinessHansen","id":"121196713"}],"hashtags":[{"start":129,"end":137,"tag":"ledelse"}]},"public_metrics":{"retweet_count":0,"reply_count":1,"like_count":0,"quote_count":0,"bookmark_count":0,"impression_count":0},"created_at":"2014-09-25T13:34:03.000Z","conversation_id":"515132123297378304","text":"Ingen forskel på M og K ledelse? Hvorfor så al den diskussion om mere ligelig fordeling? @BusinessHansen:\nhttp://t.co/OIpb4jZIPP #ledelse”","referenced_tweets":{},"attachments":{"media_keys":{}},"geo":{"place_id":"936b83f20956cd4c","coordinates":{"coordinates":{}}}},{"possibly_sensitive":false,"author_id":"251555678","id":"532995758082228225","lang":"da","edit_history_tweet_ids":["532995758082228225"],"entities":{"urls":{},"mentions":{},"hashtags":{}},"public_metrics":{"retweet_count":0,"reply_count":0,"like_count":0,"quote_count":0,"bookmark_count":0,"impression_count":0},"created_at":"2014-11-13T20:37:45.000Z","conversation_id":"532993698808987649","text":"@mortenbock nej da, er overrasket over der ikke er flere der følger mig! Men nu starter lavinen, imorgen har jeg sikkert 67 følgere!","referenced_tweets":[{"type":"replied_to","id":"532994569541935104"}],"in_reply_to_user_id":"14948213","attachments":{"media_keys":{}},"geo":{"coordinates":{"coordinates":{}}}},{"possibly_sensitive":false,"author_id":"16169838","id":"71853700108402688","lang":"da","edit_history_tweet_ids":["71853700108402688"],"entities":{"urls":{},"mentions":[{"start":0,"end":11,"username":"jesperdahl","id":"17449213"}],"hashtags":{}},"public_metrics":{"retweet_count":0,"reply_count":0,"like_count":0,"quote_count":0,"bookmark_count":0,"impression_count":0},"created_at":"2011-05-21T08:23:51.000Z","conversation_id":"71853250596454400","text":"@jesperdahl ja jeg hygger mig med min kammerat der skal prøve for første gang ;)","referenced_tweets":[{"type":"replied_to","id":"71853250596454400"}],"in_reply_to_user_id":"17449213","attachments":{"media_keys":{}},"geo":{"place_id":"b28d4ce807565ae9","coordinates":{"type":"Point","coordinates":[9.8716,57.0865]}}},{"possibly_sensitive":false,"author_id":"861857935722500096","id":"1342558042781581315","lang":"da","edit_history_tweet_ids":["1342558042781581315"],"entities":{"urls":{},"mentions":[{"start":0,"end":16,"username":"ammitzbollbille","id":"26210681"},{"start":17,"end":31,"username":"madskorsholm1","id":"1753858334694739968"}],"hashtags":{}},"public_metrics":{"retweet_count":0,"reply_count":1,"like_count":4,"quote_count":0,"bookmark_count":0,"impression_count":0},"created_at":"2020-12-25T19:49:15.000Z","conversation_id":"1342414200354844673","text":"@ammitzbollbille @Madskorsholm1 Is på, Simon Emil. Det er vist noget så uskyldigt som en joke.","referenced_tweets":[{"type":"replied_to","id":"1342557603226906626"}],"in_reply_to_user_id":"26210681","attachments":{"media_keys":{}},"geo":{"coordinates":{"coordinates":{}}}},{"possibly_sensitive":false,"author_id":"30541886","id":"966932966105591809","lang":"da","edit_history_tweet_ids":["966932966105591809"],"entities":{"urls":{},"mentions":[{"start":0,"end":12,"username":"Hestefanden","id":"954009500"},{"start":13,"end":23,"username":"tidendedk","id":"1903341626"}],"hashtags":{}},"public_metrics":{"retweet_count":0,"reply_count":1,"like_count":0,"quote_count":0,"bookmark_count":0,"impression_count":0},"created_at":"2018-02-23T07:09:18.000Z","conversation_id":"966606389320867842","text":"@Hestefanden @tidendedk Fuskere er der nok af :) vores cykel episode var i station 2 i går","referenced_tweets":[{"type":"replied_to","id":"966752920254459904"}],"in_reply_to_user_id":"954009500","attachments":{"media_keys":{}},"geo":{"coordinates":{"coordinates":{}}}},{"possibly_sensitive":false,"author_id":"23341699","id":"1094266260383240193","lang":"und","edit_history_tweet_ids":["1094266260383240193"],"entities":{"urls":{},"mentions":[{"start":0,"end":13,"username":"MagnusPharao","id":"999916548146974726"}],"hashtags":{}},"public_metrics":{"retweet_count":0,"reply_count":7,"like_count":2,"quote_count":0,"bookmark_count":0,"impression_count":0},"created_at":"2019-02-09T16:06:21.000Z","conversation_id":"1094256726898065408","text":"@MagnusPharao Ja.","referenced_tweets":[{"type":"replied_to","id":"1094259094695936000"}],"in_reply_to_user_id":"999916548146974726","attachments":{"media_keys":{}},"geo":{"coordinates":{"coordinates":{}}}},{"possibly_sensitive":false,"author_id":"595984394","id":"960245483594768384","lang":"da","edit_history_tweet_ids":["960245483594768384"],"entities":{"urls":{},"mentions":{},"hashtags":{}},"public_metrics":{"retweet_count":7,"reply_count":6,"like_count":76,"quote_count":0,"bookmark_count":0,"impression_count":0},"created_at":"2018-02-04T20:15:38.000Z","conversation_id":"960245483594768384","text":"Jeg savnede lidt, at Mette F i 21Søndag fik spørgsmålet: “Øhm...Mette, hvor skal de her lejre ligge?”","referenced_tweets":{},"attachments":{"media_keys":{}},"geo":{"coordinates":{"coordinates":{}}}},{"possibly_sensitive":false,"author_id":"92824985","id":"841947552966692864","lang":"da","edit_history_tweet_ids":["841947552966692864"],"entities":{"urls":[{"start":129,"end":152,"url":"https://t.co/IiSzDZ6xdd","expanded_url":"https://twitter.com/kinodk/status/841946551014576128","display_url":"x.com/kinodk/status/…"}],"mentions":{},"hashtags":{}},"public_metrics":{"retweet_count":0,"reply_count":1,"like_count":0,"quote_count":0,"bookmark_count":0,"impression_count":0},"created_at":"2017-03-15T09:41:53.000Z","conversation_id":"841947552966692864","text":"Normalt rebooter man succesfulde franchises. Den første var glimrende, de to andre.. Knapt så stærke, hvis jeg skal være høflig. https://t.co/IiSzDZ6xdd","referenced_tweets":[{"type":"quoted","id":"841946551014576128"}],"attachments":{"media_keys":{}},"geo":{"coordinates":{"coordinates":{}}}},{"possibly_sensitive":false,"author_id":"2212017891","id":"713773837184286720","lang":"da","edit_history_tweet_ids":["713773837184286720"],"entities":{"urls":[{"start":22,"end":45,"url":"https://t.co/AFc0tZn89n","expanded_url":"https://twitter.com/frkkahler/status/713773837184286720/photo/1","display_url":"pic.twitter.com/AFc0tZn89n","media_key":"3_713773815109652480"}],"mentions":{},"hashtags":{}},"public_metrics":{"retweet_count":0,"reply_count":3,"like_count":7,"quote_count":0,"bookmark_count":0,"impression_count":0},"created_at":"2016-03-26T17:05:18.000Z","conversation_id":"713773837184286720","text":"Perfekt krølle metode https://t.co/AFc0tZn89n","referenced_tweets":{},"attachments":{"media_keys":["3_713773815109652480"]},"geo":{"coordinates":{"coordinates":{}}}},{"possibly_sensitive":false,"author_id":"66672809","id":"1180217399754276866","lang":"da","edit_history_tweet_ids":["1180217399754276866"],"entities":{"urls":[{"start":79,"end":102,"url":"https://t.co/yU2QYl5X1c","expanded_url":"https://twitter.com/JanEliazzen/status/1180217399754276866/photo/1","display_url":"pic.twitter.com/yU2QYl5X1c","media_key":"3_1180217393781645312"}],"mentions":[{"start":0,"end":15,"username":"PabloBresciani","id":"367968877"},{"start":16,"end":32,"username":"Krystalpaladset","id":"1428074080616517634"},{"start":33,"end":43,"username":"PSkaaning","id":"110676255"},{"start":44,"end":53,"username":"quitte74","id":"29420980"},{"start":54,"end":66,"username":"stupidpussy","id":"1106040037"}],"hashtags":{}},"public_metrics":{"retweet_count":0,"reply_count":2,"like_count":6,"quote_count":0,"bookmark_count":0,"impression_count":0},"created_at":"2019-10-04T20:25:30.000Z","conversation_id":"1180217399754276866","text":"@PabloBresciani @krystalpaladset @PSkaaning @quitte74 @stupidpussy - Endelig 😍 https://t.co/yU2QYl5X1c","referenced_tweets":[{"type":"replied_to","id":"0"}],"in_reply_to_user_id":"367968877","attachments":{"media_keys":["3_1180217393781645312"]},"geo":{"coordinates":{"coordinates":{}}}},{"possibly_sensitive":false,"author_id":"326698111","id":"1430237364094480389","lang":"en","edit_history_tweet_ids":["1430237364094480389"],"entities":{"urls":{},"mentions":[{"start":0,"end":10,"username":"MonbergSF","id":"1666088336"},{"start":11,"end":23,"username":"JanEliazzen","id":"66672809"},{"start":24,"end":36,"username":"henriksen78","id":"1568470645"}],"hashtags":{}},"public_metrics":{"retweet_count":0,"reply_count":1,"like_count":0,"quote_count":0,"bookmark_count":0,"impression_count":0},"created_at":"2021-08-24T18:35:34.000Z","conversation_id":"1430207284391653376","text":"@MonbergSF @JanEliazzen @henriksen78 Couldn't care less","referenced_tweets":[{"type":"replied_to","id":"1430236884895162377"}],"in_reply_to_user_id":"1666088336","attachments":{"media_keys":{}},"geo":{"coordinates":{"coordinates":{}}}},{"possibly_sensitive":false,"author_id":"25742332","id":"912718896377073664","lang":"da","edit_history_tweet_ids":["912718896377073664"],"entities":{"urls":{},"mentions":[{"start":0,"end":10,"username":"OmnibusAU","id":"2731160126"}],"hashtags":{}},"public_metrics":{"retweet_count":0,"reply_count":1,"like_count":1,"quote_count":0,"bookmark_count":0,"impression_count":0},"created_at":"2017-09-26T16:41:57.000Z","conversation_id":"912675261149270016","text":"@OmnibusAU Jeg skal ikke længere dele kontor med en anden 😊 Og ja: Vi rykker fra Trøjborg op i Nobelparken. Godt for det sociale/kollegiale miljø","referenced_tweets":[{"type":"replied_to","id":"912690479694835714"}],"in_reply_to_user_id":"2731160126","attachments":{"media_keys":{}},"geo":{"coordinates":{"coordinates":{}}}},{"possibly_sensitive":false,"author_id":"72823792","id":"969879184825778178","lang":"da","edit_history_tweet_ids":["969879184825778178"],"entities":{"urls":[{"start":253,"end":276,"url":"https://t.co/NZHmJRfxdC","expanded_url":"http://www.justitsministeriet.dk/nyt-og-presse/pressemeddelelser/2018/nye-regler-forsvarets-hjaelp-til-politiet","display_url":"justitsministeriet.dk/nyt-og-presse/…"},{"start":277,"end":300,"url":"https://t.co/qpNic3AmDR","expanded_url":"https://twitter.com/R4nd4hl/status/969879184825778178/photo/1","display_url":"pic.twitter.com/qpNic3AmDR","media_key":"3_969879174675599360"}],"mentions":[{"start":234,"end":244,"username":"SorenPape","id":"2712091824"}],"hashtags":[{"start":246,"end":252,"tag":"dkpol"}]},"public_metrics":{"retweet_count":17,"reply_count":14,"like_count":45,"quote_count":2,"bookmark_count":0,"impression_count":0},"created_at":"2018-03-03T10:16:31.000Z","conversation_id":"969879184825778178","text":"Pape udvider militærets samarbejde med politiet, så soldater kan stå for politiarbejde som ransagninger i private hjem.\nSoldater er uddannet til at trænge ind i bygninger med chokgranater og nedkæmpe fjenden. Hvad skal de i vore hjem @SorenPape?\n#dkpol\nhttps://t.co/NZHmJRfxdC https://t.co/qpNic3AmDR","referenced_tweets":{},"attachments":{"media_keys":["3_969879174675599360"]},"geo":{"coordinates":{"coordinates":{}}}},{"possibly_sensitive":false,"author_id":"320136628","id":"1462422113369927685","lang":"da","edit_history_tweet_ids":["1462422113369927685"],"entities":{"urls":{},"mentions":{},"hashtags":{}},"public_metrics":{"retweet_count":0,"reply_count":1,"like_count":6,"quote_count":0,"bookmark_count":0,"impression_count":0},"created_at":"2021-11-21T14:06:16.000Z","conversation_id":"1462421189838741504","text":"Britta boede i Hvidovre og det var oplysninger, som burde have vakt mistanke. Men det skete ikke. I stedet ringede en af Brittas kollegaer til Britta, som var sygemeldt på det her tidspunkt. Hun fortalte Britta alt om undersøgelsen.","referenced_tweets":[{"type":"replied_to","id":"1462421812361449474"}],"in_reply_to_user_id":"320136628","attachments":{"media_keys":{}},"geo":{"coordinates":{"coordinates":{}}}},{"possibly_sensitive":false,"author_id":"104154497","id":"368277473139888128","lang":"da","edit_history_tweet_ids":["368277473139888128"],"entities":{"urls":{},"mentions":[{"start":0,"end":10,"username":"MrJokinen","id":"458383010"}],"hashtags":{}},"public_metrics":{"retweet_count":0,"reply_count":2,"like_count":0,"quote_count":0,"bookmark_count":0,"impression_count":0},"created_at":"2013-08-16T07:46:06.000Z","conversation_id":"368275899184992257","text":"@MrJokinen Er alle bannerreklamer ikke med fanfarer? Og som oftest med et lydniveau på en miliard DB...","referenced_tweets":[{"type":"replied_to","id":"368275899184992257"}],"in_reply_to_user_id":"458383010","attachments":{"media_keys":{}},"geo":{"coordinates":{"coordinates":{}}}},{"possibly_sensitive":false,"author_id":"373857508","id":"1261242363848069121","lang":"da","edit_history_tweet_ids":["1261242363848069121"],"entities":{"urls":{},"mentions":{},"hashtags":[{"start":126,"end":135,"tag":"sportfyn"}]},"public_metrics":{"retweet_count":0,"reply_count":2,"like_count":7,"quote_count":0,"bookmark_count":0,"impression_count":0},"created_at":"2020-05-15T10:29:46.000Z","conversation_id":"1261242363848069121","text":"Ungtalentet Jacob Breum kommet ind i stedet for skadet.Skjelvik. Nu ligger Lieder skadet og assistent Henrik Hansen varmer op!#sportfyn","referenced_tweets":{},"attachments":{"media_keys":{}},"geo":{"coordinates":{"coordinates":{}}}},{"possibly_sensitive":false,"author_id":"1266576756","id":"1139795311667187712","lang":"da","edit_history_tweet_ids":["1139795311667187712"],"entities":{"urls":[{"start":102,"end":125,"url":"https://t.co/tSZwtSaqdf","expanded_url":"https://twitter.com/ekrausej/status/1139795311667187712/photo/1","display_url":"pic.twitter.com/tSZwtSaqdf","media_key":"3_1139795309167403008"}],"mentions":{},"hashtags":{}},"public_metrics":{"retweet_count":0,"reply_count":2,"like_count":4,"quote_count":0,"bookmark_count":0,"impression_count":0},"created_at":"2019-06-15T07:22:33.000Z","conversation_id":"1139793250703892480","text":"Hvorfor har vi ikke et \"rødt broget\" flag, som den oprindelige betydning af dannebrog lægger op til!? https://t.co/tSZwtSaqdf","referenced_tweets":[{"type":"replied_to","id":"1139794531178680320"}],"in_reply_to_user_id":"1266576756","attachments":{"media_keys":["3_1139795309167403008"]},"geo":{"place_id":"55a020e74abc073f","coordinates":{"coordinates":{}}}},{"possibly_sensitive":false,"author_id":"152233010","id":"554737070879809539","lang":"da","edit_history_tweet_ids":["554737070879809539"],"entities":{"urls":{},"mentions":[{"start":0,"end":7,"username":"smbrix","id":"34026528"},{"start":8,"end":23,"username":"brianweichardt","id":"547416021"}],"hashtags":{}},"public_metrics":{"retweet_count":0,"reply_count":1,"like_count":0,"quote_count":0,"bookmark_count":0,"impression_count":0},"created_at":"2015-01-12T20:29:58.000Z","conversation_id":"554730337662959616","text":"@smbrix @brianweichardt En slags radiodokumentar med dækbilleder, altså. Og en pæn bil.","referenced_tweets":[{"type":"replied_to","id":"554733832893915136"}],"in_reply_to_user_id":"34026528","attachments":{"media_keys":{}},"geo":{"coordinates":{"coordinates":{}}}},{"possibly_sensitive":false,"author_id":"104165885","id":"1159851013114867713","lang":"en","edit_history_tweet_ids":["1159851013114867713"],"entities":{"urls":[{"start":278,"end":301,"url":"https://t.co/Zf0JPA9rT0","expanded_url":"https://twitter.com/lieberothdk/status/1159851013114867713/photo/1","display_url":"pic.twitter.com/Zf0JPA9rT0","media_key":"16_1159851001047912449"}],"mentions":{},"hashtags":{}},"public_metrics":{"retweet_count":0,"reply_count":4,"like_count":10,"quote_count":0,"bookmark_count":0,"impression_count":0},"created_at":"2019-08-09T15:36:45.000Z","conversation_id":"1159851013114867713","text":"Dear pizza dude. Strong feelings about topping aside, how hard can it be to do half of our pizza with no🍍, and the other half with no 🍄?\n\n“We can’t do that.” \n\nAccept the challenge, guy! I know it sounds tricky, but I think you’ll surprise yourself, if you put your mind to it! https://t.co/Zf0JPA9rT0","referenced_tweets":{},"attachments":{"media_keys":["16_1159851001047912449"]},"geo":{"coordinates":{"coordinates":{}}}},{"possibly_sensitive":false,"author_id":"1723060182","id":"792122790732259328","lang":"da","edit_history_tweet_ids":["792122790732259328"],"entities":{"urls":{},"mentions":[{"start":10,"end":20,"username":"SFpolitik","id":"28079017"},{"start":21,"end":27,"username":"imgur","id":"113211856"}],"hashtags":[{"start":96,"end":110,"tag":"detvarbaredet"}]},"public_metrics":{"retweet_count":0,"reply_count":1,"like_count":0,"quote_count":0,"bookmark_count":0,"impression_count":0},"created_at":"2016-10-28T21:56:04.000Z","conversation_id":"792061293238874112","text":"@dSeneste @SFpolitik @imgur jeg syntes ikke om reklamen. Valgkampen er i USA og ikke i Danmark. #detvarbaredet","referenced_tweets":[{"type":"replied_to","id":"792061293238874112"}],"in_reply_to_user_id":"20441701","attachments":{"media_keys":{}},"geo":{"coordinates":{"coordinates":{}}}},{"possibly_sensitive":false,"author_id":"355461219","id":"578242954143334400","lang":"da","edit_history_tweet_ids":["578242954143334400"],"entities":{"urls":{},"mentions":[{"start":0,"end":14,"username":"albrechtslund","id":"9618532"}],"hashtags":{}},"public_metrics":{"retweet_count":0,"reply_count":1,"like_count":0,"quote_count":0,"bookmark_count":0,"impression_count":0},"created_at":"2015-03-18T17:13:58.000Z","conversation_id":"578239743655354368","text":"@albrechtslund Jeg ville spørge de andre forældre. Det er under alle omstændigheder et godt tidspkt at tage fat på debat om digi medier","referenced_tweets":[{"type":"replied_to","id":"578241939419619329"}],"in_reply_to_user_id":"9618532","attachments":{"media_keys":{}},"geo":{"coordinates":{"coordinates":{}}}},{"possibly_sensitive":false,"author_id":"24731950","id":"514503896816160768","lang":"da","edit_history_tweet_ids":["514503896816160768"],"entities":{"urls":{},"mentions":[{"start":0,"end":11,"username":"Svendstrup","id":"105835167"},{"start":12,"end":24,"username":"MichaelSten","id":"113463724"}],"hashtags":{}},"public_metrics":{"retweet_count":0,"reply_count":1,"like_count":0,"quote_count":0,"bookmark_count":0,"impression_count":0},"created_at":"2014-09-23T19:57:42.000Z","conversation_id":"511499907694612480","text":"@Svendstrup @MichaelSten tsk. Har I lagt mærke til, at Ronaldo er helt færdig? Sølle syv mål i de seneste to kampe...","referenced_tweets":[{"type":"replied_to","id":"511501933950300161"}],"in_reply_to_user_id":"24731950","attachments":{"media_keys":{}},"geo":{"coordinates":{"coordinates":{}}}},{"possibly_sensitive":false,"author_id":"805874425988087811","id":"1295352413877084161","lang":"da","edit_history_tweet_ids":["1295352413877084161"],"entities":{"urls":[{"start":124,"end":147,"url":"https://t.co/h0e5W5ziTe","expanded_url":"https://twitter.com/baretraet/status/1295352413877084161/photo/1","display_url":"pic.twitter.com/h0e5W5ziTe","media_key":"16_1295352405685678081"}],"mentions":[{"start":0,"end":9,"username":"quitte74","id":"29420980"}],"hashtags":{}},"public_metrics":{"retweet_count":0,"reply_count":1,"like_count":1,"quote_count":0,"bookmark_count":0,"impression_count":0},"created_at":"2020-08-17T13:30:56.000Z","conversation_id":"1295351993473654784","text":"@quitte74 Det virker underligt. Især med tanke på husstandens yngste. Har du fundet en anden måde at slippe for beskederne? https://t.co/h0e5W5ziTe","referenced_tweets":[{"type":"replied_to","id":"1295351993473654784"}],"in_reply_to_user_id":"29420980","attachments":{"media_keys":["16_1295352405685678081"]},"geo":{"coordinates":{"coordinates":{}}}},{"possibly_sensitive":false,"author_id":"2209072900","id":"1183834750886256642","lang":"da","edit_history_tweet_ids":["1183834750886256642"],"entities":{"urls":{},"mentions":[{"start":0,"end":10,"username":"MonbergSF","id":"1666088336"},{"start":11,"end":20,"username":"twhjerne","id":"2514534995"}],"hashtags":{}},"public_metrics":{"retweet_count":0,"reply_count":1,"like_count":0,"quote_count":0,"bookmark_count":0,"impression_count":0},"created_at":"2019-10-14T19:59:33.000Z","conversation_id":"1183832086144323586","text":"@MonbergSF @twhjerne Haha super godt med illustrationer 👌 Tak for hjælpen! Nogen idé om hvorfor jeg automatisk får trends fra Holland baseret på min lokation?","referenced_tweets":[{"type":"replied_to","id":"1183833678784487426"}],"in_reply_to_user_id":"1666088336","attachments":{"media_keys":{}},"geo":{"coordinates":{"coordinates":{}}}},{"possibly_sensitive":false,"author_id":"333374097","id":"1378337979886940165","lang":"da","edit_history_tweet_ids":["1378337979886940165"],"entities":{"urls":{},"mentions":[{"start":0,"end":9,"username":"lethan87","id":"1528631432"}],"hashtags":{}},"public_metrics":{"retweet_count":0,"reply_count":2,"like_count":0,"quote_count":0,"bookmark_count":0,"impression_count":0},"created_at":"2021-04-03T13:25:57.000Z","conversation_id":"1378334549948633096","text":"@lethan87 Nej. Tror ikke der er andre der kan spytte 2-cifret i kassen som situationen er.\nRado kan muligvis lige runde den. Men så hellere ikke meget mere end det","referenced_tweets":[{"type":"replied_to","id":"1378334549948633096"}],"in_reply_to_user_id":"1528631432","attachments":{"media_keys":{}},"geo":{"coordinates":{"coordinates":{}}}},{"possibly_sensitive":false,"author_id":"35578018","id":"1222269825688514560","lang":"da","edit_history_tweet_ids":["1222269825688514560"],"entities":{"urls":{},"mentions":[{"start":0,"end":16,"username":"MortenBHojgaard","id":"1362192048"}],"hashtags":{}},"public_metrics":{"retweet_count":0,"reply_count":1,"like_count":3,"quote_count":0,"bookmark_count":0,"impression_count":0},"created_at":"2020-01-28T21:26:49.000Z","conversation_id":"1222266185833684992","text":"@MortenBHojgaard Vi har et mega fedt hold - glæder mig rigtig meget. Ville bare foretrække det foregik mere glidende end disse s#straksopbremsninger med udsalg og indkøb i et væk. At slutte 6’er i år må betragtes som fornemt alt taget i betragtning. Men sjældent den slags er godt på kort bane","referenced_tweets":[{"type":"replied_to","id":"1222269045107458050"}],"in_reply_to_user_id":"1362192048","attachments":{"media_keys":{}},"geo":{"coordinates":{"coordinates":{}}}},{"possibly_sensitive":false,"author_id":"54559040","id":"454926359190863872","lang":"da","edit_history_tweet_ids":["454926359190863872"],"entities":{"urls":{},"mentions":{},"hashtags":[{"start":111,"end":127,"tag":"OfflineOverskud"}]},"public_metrics":{"retweet_count":0,"reply_count":2,"like_count":0,"quote_count":0,"bookmark_count":0,"impression_count":0},"created_at":"2014-04-12T10:17:50.000Z","conversation_id":"454926359190863872","text":"Havde lyst til brød. Havde intet. Så måtte jeg jo bage med impro-ingredienser. Og ja, der kom hindbær i dejen! #OfflineOverskud","referenced_tweets":{},"attachments":{"media_keys":{}},"geo":{"place_id":"936b83f20956cd4c","coordinates":{"type":"Point","coordinates":[12.4975,55.7028]}}},{"possibly_sensitive":false,"author_id":"88558369","id":"1346731986430406656","lang":"da","edit_history_tweet_ids":["1346731986430406656"],"entities":{"urls":[{"start":195,"end":218,"url":"https://t.co/w1CcVnTvGU","expanded_url":"https://twitter.com/DenRigtigeMcCoy/status/1346731986430406656/photo/1","display_url":"pic.twitter.com/w1CcVnTvGU","media_key":"3_1346731982437425153"}],"mentions":[{"start":0,"end":16,"username":"Peter_Hald_CHEM","id":"989861198081425408"}],"hashtags":{}},"public_metrics":{"retweet_count":0,"reply_count":2,"like_count":0,"quote_count":0,"bookmark_count":0,"impression_count":0},"created_at":"2021-01-06T08:15:01.000Z","conversation_id":"1336951201561268225","text":"@Peter_Hald_CHEM Der er bare noget smukt over Mærsks skibe... Vi sejlede forbi et tilbage i november på vej til Sjælland med Mols Linjen - den ligner en gummibåd ved siden af sådan en Triple E 😍 https://t.co/w1CcVnTvGU","referenced_tweets":[{"type":"replied_to","id":"1346728354754547713"}],"in_reply_to_user_id":"989861198081425408","attachments":{"media_keys":["3_1346731982437425153"]},"geo":{"coordinates":{"coordinates":{}}}},{"possibly_sensitive":false,"author_id":"60885173","id":"312628695674273792","lang":"da","edit_history_tweet_ids":["312628695674273792"],"entities":{"urls":{},"mentions":{},"hashtags":{}},"public_metrics":{"retweet_count":0,"reply_count":2,"like_count":0,"quote_count":0,"bookmark_count":0,"impression_count":0},"created_at":"2013-03-15T18:17:44.000Z","conversation_id":"312628695674273792","text":"Folk som sætter sig på det yderste sæde i bussen, når begge er fri, er tabere.","referenced_tweets":{},"attachments":{"media_keys":{}},"geo":{"coordinates":{"coordinates":{}}}},{"possibly_sensitive":false,"author_id":"2215760499","id":"1265907669396791296","lang":"da","edit_history_tweet_ids":["1265907669396791296"],"entities":{"urls":[{"start":157,"end":180,"url":"https://t.co/VBR1aLEeGz","expanded_url":"https://pro.ing.dk/wastetech/artikel/plastemballage-skal-sorteres-med-formaalet-om-cirkularitet-6861","display_url":"pro.ing.dk/wastetech/arti…","status":200,"unwound_url":"https://pro.ing.dk/wastetech/holdning/plastemballage-skal-sorteres-med-formaalet-om-cirkularitet"}],"mentions":[{"start":52,"end":64,"username":"LeaWermelin","id":"606561223"},{"start":81,"end":97,"username":"plastindustrien","id":"2177807304"},{"start":185,"end":197,"username":"WasteTechDK","id":"1186266846351237122"}],"hashtags":{}},"public_metrics":{"retweet_count":4,"reply_count":3,"like_count":15,"quote_count":1,"bookmark_count":0,"impression_count":0},"created_at":"2020-05-28T07:28:02.000Z","conversation_id":"1265907669396791296","text":"Skal Danmark være førende på genanvendelse af plast @LeaWermelin? Det mener vi i @Plastindustrien: Plastemballage skal sorteres med formålet om cirkularitet https://t.co/VBR1aLEeGz via @WasteTechdk","referenced_tweets":{},"attachments":{"media_keys":{}},"geo":{"coordinates":{"coordinates":{}}}},{"possibly_sensitive":false,"author_id":"326698111","id":"1136940435493072897","lang":"da","edit_history_tweet_ids":["1136940435493072897"],"entities":{"urls":[{"start":56,"end":79,"url":"https://t.co/1OAvriSLSQ","expanded_url":"https://twitter.com/tipsbladet/status/1136939629859549184","display_url":"x.com/tipsbladet/sta…"}],"mentions":[{"start":13,"end":22,"username":"quitte74","id":"29420980"},{"start":23,"end":35,"username":"stupidpussy","id":"1106040037"},{"start":36,"end":52,"username":"Krystalpaladset","id":"1428074080616517634"}],"hashtags":{}},"public_metrics":{"retweet_count":0,"reply_count":1,"like_count":1,"quote_count":0,"bookmark_count":0,"impression_count":0},"created_at":"2019-06-07T10:18:17.000Z","conversation_id":"1136940435493072897","text":"Så er det nu @quitte74 @stupidpussy @krystalpaladset... https://t.co/1OAvriSLSQ","referenced_tweets":[{"type":"quoted","id":"1136939629859549184"}],"attachments":{"media_keys":{}},"geo":{"coordinates":{"coordinates":{}}}},{"possibly_sensitive":false,"author_id":"2805980683","id":"1414176284540870657","lang":"da","edit_history_tweet_ids":["1414176284540870657"],"entities":{"urls":{},"mentions":{},"hashtags":{}},"public_metrics":{"retweet_count":0,"reply_count":1,"like_count":4,"quote_count":0,"bookmark_count":0,"impression_count":0},"created_at":"2021-07-11T10:54:35.000Z","conversation_id":"1414157671792529408","text":"@Hemaso85 Jeg oprettede min profil for mange år siden, men fattede hat af det. \nSå kom der en epidemi og bum. Nu hænger I på mig 🤷🏻‍♀️","referenced_tweets":[{"type":"replied_to","id":"1414157674153918466"}],"in_reply_to_user_id":"2969416161","attachments":{"media_keys":{}},"geo":{"coordinates":{"coordinates":{}}}},{"possibly_sensitive":false,"author_id":"1470655698","id":"431316411118403585","lang":"da","edit_history_tweet_ids":["431316411118403585"],"entities":{"urls":{},"mentions":{},"hashtags":{}},"public_metrics":{"retweet_count":23,"reply_count":7,"like_count":22,"quote_count":0,"bookmark_count":0,"impression_count":0},"created_at":"2014-02-06T06:40:20.000Z","conversation_id":"431316411118403585","text":"Jeg kan afvise alle rygter om, at CEPOS skulle have ansat Ole Sohn :-)","referenced_tweets":{},"attachments":{"media_keys":{}},"geo":{"coordinates":{"coordinates":{}}}},{"possibly_sensitive":false,"author_id":"974889266","id":"368104189852803072","lang":"da","edit_history_tweet_ids":["368104189852803072"],"entities":{"urls":[{"start":113,"end":135,"url":"http://t.co/EBwcPojQrD","expanded_url":"https://twitter.com/RolfCRO/status/368104189852803072/photo/1","display_url":"pic.twitter.com/EBwcPojQrD","media_key":"3_368104189873758208"}],"mentions":{},"hashtags":{}},"public_metrics":{"retweet_count":16,"reply_count":7,"like_count":4,"quote_count":0,"bookmark_count":0,"impression_count":0},"created_at":"2013-08-15T20:17:32.000Z","conversation_id":"368104189852803072","text":"Vi bortgiver 5 stks. brugte el. hæve-sænke borde til spirende iværksættere! Kan afhentes i Søborg næste uge. RTG http://t.co/EBwcPojQrD","referenced_tweets":{},"attachments":{"media_keys":["3_368104189873758208"]},"geo":{"coordinates":{"coordinates":{}}}},{"possibly_sensitive":false,"author_id":"100301688","id":"713738632104902656","lang":"da","edit_history_tweet_ids":["713738632104902656"],"entities":{"urls":[{"start":94,"end":117,"url":"https://t.co/P5N6IE09Kh","expanded_url":"https://twitter.com/AmdiMadsen/status/713641383282786306","display_url":"x.com/amdimadsen/sta…"}],"mentions":{},"hashtags":[{"start":86,"end":92,"tag":"dkpol"}]},"public_metrics":{"retweet_count":1,"reply_count":1,"like_count":1,"quote_count":0,"bookmark_count":0,"impression_count":0},"created_at":"2016-03-26T14:45:25.000Z","conversation_id":"713738632104902656","text":"Således findes der urigtige/forkerte jobs i en uvirkelig verden?! Beam me up, Scott!  #dkpol  https://t.co/P5N6IE09Kh","referenced_tweets":[{"type":"quoted","id":"713641383282786306"}],"attachments":{"media_keys":{}},"geo":{"coordinates":{"coordinates":{}}}},{"possibly_sensitive":false,"author_id":"3144074691","id":"1321531082156707842","lang":"da","edit_history_tweet_ids":["1321531082156707842"],"entities":{"urls":[{"start":255,"end":278,"url":"https://t.co/jF6NSra4Ud","expanded_url":"https://www.bt.dk/samfund/soeren-brostroem-glemmer-at-spritte-af-i-traeningscenter-skal-jeg-det","display_url":"bt.dk/samfund/soeren…","status":200,"unwound_url":"https://www.bt.dk/samfund/soeren-brostroem-glemmer-at-spritte-af-i-traeningscenter-skal-jeg-det"}],"mentions":{},"hashtags":[{"start":248,"end":254,"tag":"dkpol"}]},"public_metrics":{"retweet_count":7,"reply_count":52,"like_count":33,"quote_count":7,"bookmark_count":0,"impression_count":0},"created_at":"2020-10-28T19:15:37.000Z","conversation_id":"1321531082156707842","text":"Det her er altså en smule pinligt for Søren Brostrøm. Hele den danske befolkning er lagt i skrappe rammer pga. hans anbefalinger. Og så “glemmer” han selv at følge dem. Er det restriktionerne eller den gode Brostrøm, der er forvirrende/forvirret? 🤔#dkpol https://t.co/jF6NSra4Ud","referenced_tweets":{},"attachments":{"media_keys":{}},"geo":{"coordinates":{"coordinates":{}}}},{"possibly_sensitive":false,"author_id":"53791737","id":"1390751087326633985","lang":"da","edit_history_tweet_ids":["1390751087326633985"],"entities":{"urls":{},"mentions":{},"hashtags":{}},"public_metrics":{"retweet_count":0,"reply_count":0,"like_count":1,"quote_count":0,"bookmark_count":0,"impression_count":0},"created_at":"2021-05-07T19:31:12.000Z","conversation_id":"1390750557686702080","text":"@sabrinalouisec Dig og Britney. Det må da også være lidt af et party 🙂","referenced_tweets":[{"type":"replied_to","id":"1390750557686702080"}],"in_reply_to_user_id":"315348417","attachments":{"media_keys":{}},"geo":{"coordinates":{"coordinates":{}}}},{"possibly_sensitive":false,"author_id":"3118236147","id":"987751981484830720","lang":"da","edit_history_tweet_ids":["987751981484830720"],"entities":{"urls":[{"start":117,"end":140,"url":"https://t.co/371xEx1FmW","expanded_url":"https://twitter.com/guardiolaszn/status/942107664322125824?s=21","display_url":"x.com/guardiolaszn/s…"}],"mentions":{},"hashtags":{}},"public_metrics":{"retweet_count":0,"reply_count":1,"like_count":4,"quote_count":0,"bookmark_count":0,"impression_count":0},"created_at":"2018-04-21T17:56:38.000Z","conversation_id":"987744959859183616","text":"Gult mod City for et 100% planlagt mord på KdB som any day a week burde ha’ været rødt kort og tre dage i skyggen. \n\nhttps://t.co/371xEx1FmW","referenced_tweets":[{"type":"quoted","id":"942107664322125824"},{"type":"replied_to","id":"987750153950986241"}],"in_reply_to_user_id":"3118236147","attachments":{"media_keys":{}},"geo":{"coordinates":{"coordinates":{}}}},{"possibly_sensitive":false,"author_id":"603442120","id":"1481204587868610564","lang":"da","edit_history_tweet_ids":["1481204587868610564"],"entities":{"urls":[{"start":102,"end":125,"url":"https://t.co/9Hyyh9L2Dc","expanded_url":"https://twitter.com/seatrouting/status/1481204587868610564/photo/1","display_url":"pic.twitter.com/9Hyyh9L2Dc","media_key":"3_1481204585440104451"}],"mentions":{},"hashtags":[{"start":91,"end":101,"tag":"COVID19dk"}]},"public_metrics":{"retweet_count":20,"reply_count":6,"like_count":97,"quote_count":6,"bookmark_count":2,"impression_count":0},"created_at":"2022-01-12T10:01:07.000Z","conversation_id":"1481204587868610564","text":"Lad nu være med at fortsætte ned af den boostervej. Det er noget skidteras - på godt jysk.\n#COVID19dk https://t.co/9Hyyh9L2Dc","referenced_tweets":{},"attachments":{"media_keys":["3_1481204585440104451"]},"geo":{"place_id":"936b83f20956cd4c","coordinates":{"coordinates":{}}}},{"possibly_sensitive":false,"author_id":"90762795","id":"335117000596676608","lang":"da","edit_history_tweet_ids":["335117000596676608"],"entities":{"urls":{},"mentions":[{"start":8,"end":22,"username":"fallulahmusic","id":"119890574"}],"hashtags":[{"start":110,"end":116,"tag":"escdk"},{"start":117,"end":123,"tag":"mgpdk"},{"start":124,"end":135,"tag":"eurovision"}]},"public_metrics":{"retweet_count":0,"reply_count":1,"like_count":0,"quote_count":0,"bookmark_count":0,"impression_count":0},"created_at":"2013-05-16T19:38:13.000Z","conversation_id":"335117000596676608","text":"Stiller @Fallulahmusic's storesøster op for Bulgarien i år, sammen med Morten fra Safri Duo ? Jeg er i chok.. #escdk #mgpdk #eurovision","referenced_tweets":{},"attachments":{"media_keys":{}},"geo":{"coordinates":{"coordinates":{}}}},{"possibly_sensitive":false,"author_id":"859552898","id":"1018916665722134528","lang":"da","edit_history_tweet_ids":["1018916665722134528"],"entities":{"urls":{},"mentions":{},"hashtags":[{"start":107,"end":115,"tag":"fcklive"}]},"public_metrics":{"retweet_count":0,"reply_count":3,"like_count":8,"quote_count":0,"bookmark_count":0,"impression_count":0},"created_at":"2018-07-16T17:53:58.000Z","conversation_id":"1018916665722134528","text":"Og jeg hader åbenbart stadig fodbold. Gør mig mentalt klar til endnu sådan en sæson. Fuck det er elendigt. #fcklive","referenced_tweets":{},"attachments":{"media_keys":{}},"geo":{"coordinates":{"coordinates":{}}}},{"possibly_sensitive":false,"author_id":"533345539","id":"1473979533195948032","lang":"da","edit_history_tweet_ids":["1473979533195948032"],"entities":{"urls":[{"start":73,"end":96,"url":"https://t.co/qlABHFg7aS","expanded_url":"https://twitter.com/KirstineAavang/status/1473979533195948032/photo/1","display_url":"pic.twitter.com/qlABHFg7aS","media_key":"16_1473979525373513740"}],"mentions":{},"hashtags":{}},"public_metrics":{"retweet_count":0,"reply_count":5,"like_count":30,"quote_count":0,"bookmark_count":0,"impression_count":0},"created_at":"2021-12-23T11:31:20.000Z","conversation_id":"1473979533195948032","text":"Ny juletradition: ligesom sidste år til jul er jeg nu smittet med covid. https://t.co/qlABHFg7aS","referenced_tweets":{},"attachments":{"media_keys":["16_1473979525373513740"]},"geo":{"coordinates":{"coordinates":{}}}},{"possibly_sensitive":false,"author_id":"370631593","id":"1486369189493415942","lang":"da","edit_history_tweet_ids":["1486369189493415942"],"entities":{"urls":[{"start":96,"end":119,"url":"https://t.co/pwxv5dh9GB","expanded_url":"https://www.infectioncontroltoday.com/view/cloth-masks-are-useless-against-covid-19-redux-omicron-version","display_url":"infectioncontroltoday.com/view/cloth-mas…"}],"mentions":[{"start":0,"end":13,"username":"MagnusPharao","id":"999916548146974726"},{"start":14,"end":23,"username":"mortenkj","id":"636144198"},{"start":24,"end":34,"username":"Gravelezz","id":"1639165920374292482"},{"start":35,"end":47,"username":"LBMathiesen","id":"980721900"},{"start":48,"end":60,"username":"dkpolparrot","id":"2827328289"}],"hashtags":{}},"public_metrics":{"retweet_count":0,"reply_count":1,"like_count":0,"quote_count":0,"bookmark_count":0,"impression_count":0},"created_at":"2022-01-26T16:03:24.000Z","conversation_id":"1486279685176807424","text":"@MagnusPharao @mortenkj @Gravelezz @LBMathiesen @dkpolparrot Husk nu at vi snakker om omikron \n\nhttps://t.co/pwxv5dh9GB","referenced_tweets":[{"type":"replied_to","id":"1486366452001263617"}],"in_reply_to_user_id":"999916548146974726","attachments":{"media_keys":{}},"geo":{"coordinates":{"coordinates":{}}}},{"possibly_sensitive":false,"author_id":"81656170","id":"907260186431295488","lang":"da","edit_history_tweet_ids":["907260186431295488"],"entities":{"urls":{},"mentions":{},"hashtags":[{"start":75,"end":81,"tag":"dkpol"}]},"public_metrics":{"retweet_count":40,"reply_count":15,"like_count":254,"quote_count":3,"bookmark_count":0,"impression_count":0},"created_at":"2017-09-11T15:10:59.000Z","conversation_id":"907260186431295488","text":"Dette er så fucked up! \nVille ønske, det var indvandrere, der stod bag, så #dkpol ville gøre noget ved det\n https://t.co/6AKxFswBvL?amp=1","referenced_tweets":{},"attachments":{"media_keys":{}},"geo":{"coordinates":{"coordinates":{}}}},{"possibly_sensitive":false,"author_id":"1261433694","id":"1313392058904834048","lang":"da","edit_history_tweet_ids":["1313392058904834048"],"entities":{"urls":{},"mentions":[{"start":0,"end":16,"username":"MortenBHojgaard","id":"1362192048"}],"hashtags":{}},"public_metrics":{"retweet_count":0,"reply_count":1,"like_count":0,"quote_count":0,"bookmark_count":0,"impression_count":0},"created_at":"2020-10-06T08:14:03.000Z","conversation_id":"1313387256133177344","text":"@MortenBHojgaard Præcis, iflg. Transfermarkt er der et par fine frie transfers at hente på VB, 2 fra Skandinavien, den ene deler dog agent med Jørgen og Miiko Albornoz bør være interessant for andre klubber. Alternativt kaster man Brems for løverne.","referenced_tweets":[{"type":"replied_to","id":"1313390716639420417"}],"in_reply_to_user_id":"1362192048","attachments":{"media_keys":{}},"geo":{"coordinates":{"coordinates":{}}}},{"possibly_sensitive":false,"author_id":"1090289444","id":"1095652796010037249","lang":"da","edit_history_tweet_ids":["1095652796010037249"],"entities":{"urls":{},"mentions":[{"start":0,"end":8,"username":"koefoed","id":"22815017"}],"hashtags":{}},"public_metrics":{"retweet_count":0,"reply_count":2,"like_count":0,"quote_count":0,"bookmark_count":0,"impression_count":0},"created_at":"2019-02-13T11:55:57.000Z","conversation_id":"1095648226743586816","text":"@koefoed Jeg har dem liggende i låget fra en kopipapirkasse. Den har lige den rette størrelse.","referenced_tweets":[{"type":"replied_to","id":"1095649821661282305"}],"in_reply_to_user_id":"22815017","attachments":{"media_keys":{}},"geo":{"coordinates":{"coordinates":{}}}},{"possibly_sensitive":false,"author_id":"33841407","id":"63578956271599616","lang":"da","edit_history_tweet_ids":["63578956271599616"],"entities":{"urls":{},"mentions":{},"hashtags":[{"start":112,"end":117,"tag":"KLIK"},{"start":118,"end":127,"tag":"Redesign"},{"start":128,"end":139,"tag":"LessIsMore"}]},"public_metrics":{"retweet_count":0,"reply_count":0,"like_count":0,"quote_count":0,"bookmark_count":0,"impression_count":0},"created_at":"2011-04-28T12:22:59.000Z","conversation_id":"63578956271599616","text":"http://louisekampmann.dk/ - Så er der blevet ryddet op og lavet cirkler - \nVær velkommen i Louise's link-land \n\n#KLIK #Redesign #LessIsMore","referenced_tweets":{},"attachments":{"media_keys":{}},"geo":{"coordinates":{"coordinates":{}}}},{"possibly_sensitive":false,"author_id":"155584627","id":"1168963731344244737","lang":"da","edit_history_tweet_ids":["1168963731344244737"],"entities":{"urls":[{"start":28,"end":51,"url":"https://t.co/PGJZwRh36A","expanded_url":"https://jyllands-posten.dk/premium/indblik/Indland/ECE11592052/naar-pilen-peger-paa-en-skal-man-tage-ansvar/","display_url":"jyllands-posten.dk/premium/indbli…","unwound_url":"https://jyllands-posten.dk/premium/indblik/Indland/ECE11592052/naar-pilen-peger-paa-en-skal-man-tage-ansvar/"}],"mentions":{},"hashtags":{}},"public_metrics":{"retweet_count":40,"reply_count":134,"like_count":1325,"quote_count":22,"bookmark_count":1,"impression_count":0},"created_at":"2019-09-03T19:07:26.000Z","conversation_id":"1168963731344244737","text":"Så er katten ude af sækken. https://t.co/PGJZwRh36A","referenced_tweets":{},"attachments":{"media_keys":{}},"geo":{"coordinates":{"coordinates":{}}}},{"possibly_sensitive":false,"author_id":"2516315844","id":"1330230493946720267","lang":"qam","edit_history_tweet_ids":["1330230493946720267"],"entities":{"urls":{},"mentions":[{"start":0,"end":9,"username":"quitte74","id":"29420980"}],"hashtags":{}},"public_metrics":{"retweet_count":0,"reply_count":1,"like_count":0,"quote_count":0,"bookmark_count":0,"impression_count":0},"created_at":"2020-11-21T19:23:58.000Z","conversation_id":"1330230440414867465","text":"@quitte74 ???","referenced_tweets":[{"type":"replied_to","id":"1330230440414867465"}],"in_reply_to_user_id":"29420980","attachments":{"media_keys":{}},"geo":{"coordinates":{"coordinates":{}}}},{"possibly_sensitive":false,"author_id":"2548119608","id":"543122790061465601","lang":"da","edit_history_tweet_ids":["543122790061465601"],"entities":{"urls":{},"mentions":{},"hashtags":[{"start":53,"end":58,"tag":"eldk"},{"start":59,"end":66,"tag":"fcktor"}]},"public_metrics":{"retweet_count":0,"reply_count":5,"like_count":7,"quote_count":0,"bookmark_count":0,"impression_count":0},"created_at":"2014-12-11T19:18:58.000Z","conversation_id":"543122790061465601","text":"Er der stadig danske tilskuere tilbage i Parken ...?\n#eldk #fcktor","referenced_tweets":{},"attachments":{"media_keys":{}},"geo":{"coordinates":{"coordinates":{}}}},{"possibly_sensitive":false,"author_id":"28367314","id":"209014559107846145","lang":"da","edit_history_tweet_ids":["209014559107846145"],"entities":{"urls":{},"mentions":{},"hashtags":{}},"public_metrics":{"retweet_count":0,"reply_count":0,"like_count":0,"quote_count":0,"bookmark_count":0,"impression_count":0},"created_at":"2012-06-02T20:12:08.000Z","conversation_id":"209014559107846145","text":"@BekkaMie HAHAHA ja. Min mor ville falde død om hvis hun så de beskeder her xD","referenced_tweets":[{"type":"replied_to","id":"0"}],"in_reply_to_user_id":"487697877","attachments":{"media_keys":{}},"geo":{"coordinates":{"coordinates":{}}}},{"possibly_sensitive":false,"author_id":"256718199","id":"996104387662635008","lang":"da","edit_history_tweet_ids":["996104387662635008"],"entities":{"urls":{},"mentions":[{"start":0,"end":9,"username":"rasmusmp","id":"49733663"}],"hashtags":{}},"public_metrics":{"retweet_count":0,"reply_count":2,"like_count":0,"quote_count":0,"bookmark_count":0,"impression_count":0},"created_at":"2018-05-14T19:06:07.000Z","conversation_id":"996102585336688640","text":"@rasmusmp Horsens, der har på samvittigheden, at Brøndby IKKE rykkede ned i sin tid? 😏","referenced_tweets":[{"type":"replied_to","id":"996103976503447552"}],"in_reply_to_user_id":"49733663","attachments":{"media_keys":{}},"geo":{"coordinates":{"coordinates":{}}}},{"possibly_sensitive":false,"author_id":"2941384588","id":"1313577152042991620","lang":"da","edit_history_tweet_ids":["1313577152042991620"],"entities":{"urls":{},"mentions":{},"hashtags":{}},"public_metrics":{"retweet_count":0,"reply_count":3,"like_count":31,"quote_count":0,"bookmark_count":0,"impression_count":0},"created_at":"2020-10-06T20:29:32.000Z","conversation_id":"1313577152042991620","text":"Taber 1-2 i vores første fragleague kamp. \n\nVi vinder en overpass på 16-6 og smider derefter 2 kæmpe føringer som fører videre til en tabt OT og en 14-16 :( \n\nHård dag, men vi arbejder bare hårdere og vinder de næste kampe! \n\nEither you win or you learn, today we learned.","referenced_tweets":{},"attachments":{"media_keys":{}},"geo":{"coordinates":{"coordinates":{}}}},{"possibly_sensitive":false,"author_id":"835144095165202433","id":"1202642591197679618","lang":"da","edit_history_tweet_ids":["1202642591197679618"],"entities":{"urls":{},"mentions":[{"start":0,"end":10,"username":"baretraet","id":"805874425988087811"}],"hashtags":{}},"public_metrics":{"retweet_count":0,"reply_count":1,"like_count":1,"quote_count":0,"bookmark_count":0,"impression_count":0},"created_at":"2019-12-05T17:35:12.000Z","conversation_id":"1202642208572215296","text":"@baretraet Har du selv lavet det i paint? 😂","referenced_tweets":[{"type":"replied_to","id":"1202642208572215296"}],"in_reply_to_user_id":"805874425988087811","attachments":{"media_keys":{}},"geo":{"place_id":"315be5b98a49ae29","coordinates":{"coordinates":{}}}},{"possibly_sensitive":false,"author_id":"36741289","id":"1369257893216858113","lang":"da","edit_history_tweet_ids":["1369257893216858113"],"entities":{"urls":[{"start":142,"end":165,"url":"https://t.co/YJdnEeHEZ9","expanded_url":"https://twitter.com/henrik_ullum/status/1369012744641449989","display_url":"x.com/henrik_ullum/s…"}],"mentions":{},"hashtags":[{"start":135,"end":141,"tag":"dkpol"}]},"public_metrics":{"retweet_count":2,"reply_count":1,"like_count":5,"quote_count":0,"bookmark_count":0,"impression_count":0},"created_at":"2021-03-09T12:04:55.000Z","conversation_id":"1369257893216858113","text":"Og derfor skal skolebørnene også tilbage til skolen. Nu. Efter- og højskoler i bobler. Og genåbning af serviceerhverv. Hver dag tæller #dkpol https://t.co/YJdnEeHEZ9","referenced_tweets":[{"type":"quoted","id":"1369012744641449989"}],"attachments":{"media_keys":{}},"geo":{"place_id":"936b83f20956cd4c","coordinates":{"coordinates":{}}}},{"possibly_sensitive":false,"author_id":"169078217","id":"608168738052034560","lang":"qme","edit_history_tweet_ids":["608168738052034560"],"entities":{"urls":[{"start":11,"end":33,"url":"http://t.co/1jvoSC7IaO","expanded_url":"https://twitter.com/johslangkilde/status/608168738052034560/photo/1","display_url":"pic.twitter.com/1jvoSC7IaO","media_key":"3_608168722017034242"}],"mentions":{},"hashtags":[{"start":0,"end":10,"tag":"Halsbrand"}]},"public_metrics":{"retweet_count":0,"reply_count":2,"like_count":9,"quote_count":0,"bookmark_count":0,"impression_count":0},"created_at":"2015-06-09T07:08:21.000Z","conversation_id":"608168738052034560","text":"#Halsbrand http://t.co/1jvoSC7IaO","referenced_tweets":{},"attachments":{"media_keys":["3_608168722017034242"]},"geo":{"coordinates":{"coordinates":{}}}},{"possibly_sensitive":false,"author_id":"31677464","id":"991673252861837312","lang":"da","edit_history_tweet_ids":["991673252861837312"],"entities":{"urls":{},"mentions":[{"start":0,"end":14,"username":"SLO_BrondbyIF","id":"3945783263"}],"hashtags":{}},"public_metrics":{"retweet_count":0,"reply_count":3,"like_count":0,"quote_count":0,"bookmark_count":0,"impression_count":0},"created_at":"2018-05-02T13:38:22.000Z","conversation_id":"991673252861837312","text":"@SLO_BrondbyIF Kom igennem køen, men havnede på Sæsonkort stedet og skulle taste sæsonkort???!!!???","referenced_tweets":[{"type":"replied_to","id":"0"}],"in_reply_to_user_id":"3945783263","attachments":{"media_keys":{}},"geo":{"coordinates":{"coordinates":{}}}},{"possibly_sensitive":false,"author_id":"40487207","id":"5737211160952832","lang":"da","edit_history_tweet_ids":["5737211160952832"],"entities":{"urls":{},"mentions":{},"hashtags":{}},"public_metrics":{"retweet_count":0,"reply_count":0,"like_count":0,"quote_count":0,"bookmark_count":0,"impression_count":0},"created_at":"2010-11-19T21:40:32.000Z","conversation_id":"5737211160952832","text":"Klokken er ikke engang 23 og jeg har udsyn til 5 dinglende dillertjawser. Det bliver vist en god bytur.","referenced_tweets":{},"attachments":{"media_keys":{}},"geo":{"coordinates":{"coordinates":{}}}},{"possibly_sensitive":false,"author_id":"1028244217","id":"478568782076862464","lang":"da","edit_history_tweet_ids":["478568782076862464"],"entities":{"urls":{},"mentions":{},"hashtags":[{"start":125,"end":136,"tag":"aalborgpol"}]},"public_metrics":{"retweet_count":0,"reply_count":1,"like_count":0,"quote_count":0,"bookmark_count":0,"impression_count":0},"created_at":"2014-06-16T16:04:23.000Z","conversation_id":"478568782076862464","text":"Så lagde SD sig fladt ned for Tulip i sagen om store ammoniaklagre i Aalborg centrum og fulgte Venstre ud i uansvarligheden. #aalborgpol","referenced_tweets":{},"attachments":{"media_keys":{}},"geo":{"coordinates":{"coordinates":{}}}},{"possibly_sensitive":false,"author_id":"2396706266","id":"651755278464122880","lang":"da","edit_history_tweet_ids":["651755278464122880"],"entities":{"urls":{},"mentions":[{"start":0,"end":12,"username":"Hestefanden","id":"954009500"},{"start":44,"end":54,"username":"mxnyheder","id":"25998817"}],"hashtags":{}},"public_metrics":{"retweet_count":0,"reply_count":1,"like_count":1,"quote_count":0,"bookmark_count":0,"impression_count":0},"created_at":"2015-10-07T13:45:42.000Z","conversation_id":"651736320759472128","text":"@Hestefanden Jeg troede er kort øjeblik, at @mxnyheder havde skrevet historien \"100 DRIKKESELFIES: SE DENNE SJOVE BORNHOLMERS INSTAGRAM\"","referenced_tweets":[{"type":"replied_to","id":"651736320759472128"}],"in_reply_to_user_id":"954009500","attachments":{"media_keys":{}},"geo":{"coordinates":{"coordinates":{}}}}]
