{
  "authorName": "Gorm Anker GunnarsenGorm Anker GunnarsenGorm Anker GunnarsenThomas Friis J칮rgensenThomas Friis J칮rgensenThomas Friis J칮rgensen",
  "authorId": "gorm.gunnarsen",
  "text": "Turen rundt om Amager er blevet l칝ngere. Det er en ueksponeret konsekvens af opd칝mningen af Kongedybet.\nDet er godt, at d칝mningens skadelige indvirkning p친 칒resunds milj칮, dens p친virkning af 칒sters칮ens saltindhold og dens for칮gelse af risikoen for stormflod i Inderhavnen er mere eksponerede.\nMen det er alligevel lidt irriterende, at der er l칝ngere rundt, selv om dagens tur rundt om Amager var fyldt med herlige naturoplevelser i godt selskab.\nEn af de bedre ting var at l칝re strandkarse at kende. Min rejsekammerat l칝rte mig flere nyttige ting - og strandkarse smager forrygende.",
  "hasMedia": true,
  "mediaUrl": "https://www.facebook.com/photo/?fbid=10171081929272037&amp;set=pcb.10171082089872037&amp;__cft__[0]=AZXW4enmKow_swXDwcx4K3qhy0vCLypeT3cUk3n59dg3fTLPna0b_v4gx13MknX_vvD6r1fdcrTlO8fh-wQ_JwB2c09fGaeXTG8kB_0SHd6eKlpq_GLnMQAk7k-SPvYcFJE&amp;__tn__=*bH-R",
  "mediaText": "",
  "reactions": [
    {
      "type": "like",
      "count": "68"
    }
  ],
  "comments": [
    {
      "id": "162308483259654",
      "parentId": null,
      "authorName": "Henriette Brockdorff",
      "authorId": "henriette.brockdorff.1",
      "timeLabel": "Kommentar fra Henriette Brockdorff for 2 dage siden",
      "text": "Lyder som en dejlig tur",
      "hasMedia": false,
      "mediaAltText": null,
      "mediaUrl": null,
      "reactions": {
        "totalCount": 1,
        "types": [
          "like"
        ]
      }
    },
    {
      "id": "799650101380197",
      "parentId": null,
      "authorName": "Vilmer Andersen",
      "authorId": "vilmer.andersen.5",
      "timeLabel": "Kommentar fra Vilmer Andersen for 2 dage siden",
      "text": "Selv p친 dybt vand - godt padlet kammerat",
      "hasMedia": false,
      "mediaAltText": null,
      "mediaUrl": null,
      "reactions": {
        "totalCount": 1,
        "types": [
          "heart"
        ]
      }
    },
    {
      "id": "782184823410716",
      "parentId": null,
      "authorName": "Anna Katarina Rosenblad",
      "authorId": "anna.rosenblad",
      "timeLabel": "Kommentar fra Anna Katarina Rosenblad for 2 dage siden",
      "text": "Det er god motion med mange flotte oplevelser, p친 trods af d칝mning.",
      "hasMedia": false,
      "mediaAltText": null,
      "mediaUrl": null,
      "reactions": {
        "totalCount": 1,
        "types": [
          "like"
        ]
      }
    },
    {
      "id": "944990743314417",
      "parentId": null,
      "authorName": "J칮rgen Hilm",
      "authorId": "profile.php",
      "timeLabel": "Kommentar fra J칮rgen Hilm for 56 minutter siden",
      "text": "Sejt padlet, respekt gamle Gorm\n游눩游낕游냛游녨游낕",
      "hasMedia": false,
      "mediaAltText": null,
      "mediaUrl": null,
      "reactions": {
        "totalCount": 0,
        "types": []
      }
    }
  ]
}