{
  "authorName": "Helle BonnesenHelle BonnesenHelle Bonnesen Kroppedal MuseumKroppedal MuseumKroppedal Museum",
  "authorId": "hellebonnesen.fk",
  "text": "Ny museumsreform er på vej!\nTuren gik til Kroppedal i Taastrup for at diskutere udfordringer og muligheder for en ny reform med museumsdirektør Mads Thernøe samt Lars Gravgaard og Finn Søder.\nTusind tak for et godt møde og for en fin rundvisning blandt både vikinghistorien på Vestegnen og Rømers fantastiske historie om lys.",
  "hasMedia": true,
  "mediaUrl": "https://www.facebook.com/photo/?fbid=722650756536219&amp;set=a.228231082644858&amp;__cft__[0]=AZVgGSv66wre_olzhB67Gem9iX8cGJnXIn73NHWywdx4EZd2TyZvVib1zSfRZuG_RPu71rhVfNZB2XND6PRf9ZL8J_bZHbaLOjekKu_6PBcy_5446EGovxNB8cOfRGmSqwZDubP-04q-AaC78s4QkPC4&amp;__tn__=EH-R",
  "mediaText": "Kan være et billede af 4 personer og tekst, der siger &quot;KROPPEDAL MUS MUSSUM EUM&quot;",
  "reactions": [
    {
      "type": "like",
      "count": "21"
    }
  ],
  "comments": []
}